azoni/__init__.py
azoni/module1.py
azoni-0.1.4.dist-info/METADATA
azoni-0.1.4.dist-info/WHEEL
azoni-0.1.4.dist-info/top_level.txt
azoni-0.1.4.dist-info/RECORD
