Metadata-Version: 2.1
Name: azoni
Version: 0.1.4
Summary: azoni test agent
Home-page: https://github.com/azoni/azoni-package
Author: Azoni
Author-email: azoninft@gmail.com
License: MIT
Classifier: Programming Language :: Python :: 3
Classifier: License :: OSI Approved :: MIT License
Classifier: Operating System :: OS Independent
Requires-Python: >=3.6
